SklearnYuTensorflowJiqiXuexiShiyongZhinanDierBanFix1Fix1/README.md
SklearnYuTensorflowJiqiXuexiShiyongZhinanDierBanFix1Fix1/__init__.py
SklearnYuTensorflowJiqiXuexiShiyongZhinanDierBanFix1Fix1/__main__.py
SklearnYuTensorflowJiqiXuexiShiyongZhinanDierBanFix1Fix1/file.epub
SklearnYuTensorflowJiqiXuexiShiyongZhinanDierBanFix1Fix1/index.html
SklearnYuTensorflowJiqiXuexiShiyongZhinanDierBanFix1Fix1/css/__init__.py
SklearnYuTensorflowJiqiXuexiShiyongZhinanDierBanFix1Fix1/css/annotations.css
SklearnYuTensorflowJiqiXuexiShiyongZhinanDierBanFix1Fix1/css/main.css
SklearnYuTensorflowJiqiXuexiShiyongZhinanDierBanFix1Fix1/css/normalize.css
SklearnYuTensorflowJiqiXuexiShiyongZhinanDierBanFix1Fix1/css/popup.css
SklearnYuTensorflowJiqiXuexiShiyongZhinanDierBanFix1Fix1/font/__init__.py
SklearnYuTensorflowJiqiXuexiShiyongZhinanDierBanFix1Fix1/font/fontello.eot
SklearnYuTensorflowJiqiXuexiShiyongZhinanDierBanFix1Fix1/font/fontello.svg
SklearnYuTensorflowJiqiXuexiShiyongZhinanDierBanFix1Fix1/font/fontello.ttf
SklearnYuTensorflowJiqiXuexiShiyongZhinanDierBanFix1Fix1/font/fontello.woff
SklearnYuTensorflowJiqiXuexiShiyongZhinanDierBanFix1Fix1/img/__init__.py
SklearnYuTensorflowJiqiXuexiShiyongZhinanDierBanFix1Fix1/img/annotator-glyph-sprite.png
SklearnYuTensorflowJiqiXuexiShiyongZhinanDierBanFix1Fix1/img/annotator-icon-sprite.png
SklearnYuTensorflowJiqiXuexiShiyongZhinanDierBanFix1Fix1/img/apple-touch-icon.png
SklearnYuTensorflowJiqiXuexiShiyongZhinanDierBanFix1Fix1/img/cancelfullscreen.png
SklearnYuTensorflowJiqiXuexiShiyongZhinanDierBanFix1Fix1/img/close.png
SklearnYuTensorflowJiqiXuexiShiyongZhinanDierBanFix1Fix1/img/fullscreen.png
SklearnYuTensorflowJiqiXuexiShiyongZhinanDierBanFix1Fix1/img/loader.gif
SklearnYuTensorflowJiqiXuexiShiyongZhinanDierBanFix1Fix1/img/menu-icon.png
SklearnYuTensorflowJiqiXuexiShiyongZhinanDierBanFix1Fix1/img/save.png
SklearnYuTensorflowJiqiXuexiShiyongZhinanDierBanFix1Fix1/img/saved.png
sklearn_yu_tensorflow_jiqi_xuexi_shiyong_zhinan_dier_ban_fix1_fix1-2025.3.25.1.dist-info/METADATA
sklearn_yu_tensorflow_jiqi_xuexi_shiyong_zhinan_dier_ban_fix1_fix1-2025.3.25.1.dist-info/WHEEL
sklearn_yu_tensorflow_jiqi_xuexi_shiyong_zhinan_dier_ban_fix1_fix1-2025.3.25.1.dist-info/entry_points.txt
sklearn_yu_tensorflow_jiqi_xuexi_shiyong_zhinan_dier_ban_fix1_fix1-2025.3.25.1.dist-info/top_level.txt
sklearn_yu_tensorflow_jiqi_xuexi_shiyong_zhinan_dier_ban_fix1_fix1-2025.3.25.1.dist-info/RECORD
